psaithon/__init__.py
psaithon/_version.py
psaithon/cli.py
psaithon-0.1.0.dist-info/AUTHORS.rst
psaithon-0.1.0.dist-info/LICENSE
psaithon-0.1.0.dist-info/METADATA
psaithon-0.1.0.dist-info/WHEEL
psaithon-0.1.0.dist-info/entry_points.txt
psaithon-0.1.0.dist-info/top_level.txt
psaithon-0.1.0.dist-info/RECORD
