Metadata-Version: 2.1
Name: psaithon
Version: 0.1.0
Summary: Psaithon is an experimental effort to successfully upload a package to PYPI.
Home-page: https://github.com/sayan1999/psaithon
Author: Sayan Dey
Author-email: mr.sayan.dey@gmail.com
License: MIT
Platform: UNKNOWN
Classifier: Development Status :: 2 - Pre-Alpha
Classifier: Intended Audience :: Developers
Classifier: License :: OSI Approved :: MIT License
Classifier: Natural Language :: English
Classifier: Programming Language :: Python :: 2
Classifier: Programming Language :: Python :: 2.7
Classifier: Programming Language :: Python :: 3
Classifier: Programming Language :: Python :: 3.3
Classifier: Programming Language :: Python :: 3.4
Classifier: Programming Language :: Python :: 3.5
Requires-Dist: click
